fastimport/__init__.py
fastimport/commands.py
fastimport/dates.py
fastimport/errors.py
fastimport/helpers.py
fastimport/parser.py
fastimport/processor.py
fastimport/py.typed
fastimport/reftracker.py
fastimport/processors/__init__.py
fastimport/processors/filter_processor.py
fastimport/processors/info_processor.py
fastimport/processors/query_processor.py
fastimport-0.9.16.data/scripts/fast-import-filter
fastimport-0.9.16.data/scripts/fast-import-info
fastimport-0.9.16.data/scripts/fast-import-query
fastimport-0.9.16.dist-info/licenses/AUTHORS
fastimport-0.9.16.dist-info/licenses/COPYING
fastimport-0.9.16.dist-info/METADATA
fastimport-0.9.16.dist-info/WHEEL
fastimport-0.9.16.dist-info/top_level.txt
fastimport-0.9.16.dist-info/RECORD
