Metadata-Version: 2.4
Name: fastimport
Version: 0.9.16
Summary: VCS fastimport/fastexport parser
Author-email: Canonical Ltd <bazaar@lists.canonical.com>
Maintainer-email: Jelmer Vernooij <jelmer@jelmer.uk>
License: GNU GPL v2 or later
Project-URL: Homepage, https://github.com/jelmer/python-fastimport
Project-URL: Repository, https://github.com/jelmer/python-fastimport
Classifier: Development Status :: 4 - Beta
Classifier: License :: OSI Approved :: GNU General Public License v2 or later (GPLv2+)
Classifier: Programming Language :: Python :: 3.9
Classifier: Programming Language :: Python :: 3.10
Classifier: Programming Language :: Python :: 3.11
Classifier: Programming Language :: Python :: 3.12
Classifier: Programming Language :: Python :: 3.13
Classifier: Programming Language :: Python :: Implementation :: CPython
Classifier: Programming Language :: Python :: Implementation :: PyPy
Classifier: Operating System :: POSIX
Classifier: Topic :: Software Development :: Version Control
Requires-Python: >=3.9
License-File: COPYING
License-File: AUTHORS
Dynamic: license-file
